s3interactions/__init__.py
s3interactions/s3_download.py
s3interactions/s3_interactions.py
s3interactions/s3_storage.py
s3interactions-0.2.0.dist-info/WHEEL
s3interactions-0.2.0.dist-info/METADATA
s3interactions-0.2.0.dist-info/RECORD
